ht2/__init__.py
ht2/ml_utils/transform_funcs.py
ht2/ml_utils/transforms.py
ht2/schemas/basic.py
ht2/scripts/htio.py
ht2/tools/download_hf_dataset.py
ht2/tools/download_hf_model.py
ht2/tools/download_hf_tokenizer.py
ht2/tools/htio_ops.py
ht2/tools/labeling_ops.py
ht2/tools/ocr_labeler.py
ht2/utils_dev/converts.py
ht2/utils_dev/example.py
ht2/utils_dev/files.py
ht2/utils_dev/img_augs.py
ht2/utils_dev/misc.py
ht2/utils_dev/os.py
ht2/utils_dev/text.py
ht2/utils_dev/visualize.py
ht2-0.2.5.dist-info/LICENSE
ht2-0.2.5.dist-info/METADATA
ht2-0.2.5.dist-info/WHEEL
ht2-0.2.5.dist-info/entry_points.txt
ht2-0.2.5.dist-info/top_level.txt
ht2-0.2.5.dist-info/RECORD
