Metadata-Version: 2.1
Name: ht2
Version: 0.2.5
Summary: Just a bag of quality of life tools for Machine Learning Engineers
Author-email: Haotian Zhang <z.haotian@columbia.edu>
Project-URL: Homepage, https://github.com/htplex/ht2
Project-URL: Bug Tracker, https://github.com/htplex/ht2/issues
Classifier: Programming Language :: Python :: 3
Classifier: License :: OSI Approved :: MIT License
Classifier: Operating System :: OS Independent
Requires-Python: >=3.7
License-File: LICENSE
Requires-Dist: opencv-python
Requires-Dist: matplotlib
Requires-Dist: numpy
Requires-Dist: lmdb
Requires-Dist: msgpack
Requires-Dist: msgpack-numpy
Requires-Dist: tqdm
Requires-Dist: lz4
